Workbook

Sheet Issues
A1: Ticket ID | B1: GH # | C1: Title | D1: Module | E1: Epic | F1: Priority | G1: Phase | H1: Size | I1: Est. days | J1: Cut | K1: Area | L1: Status | M1: Assignees | N1: State | O1: Blocked by | P1: Open blockers | Q1: Link
A2: ADM-L01 | B2: 205 | C2: [ADMIN] Build the platform admin console | D2: admin | E2: [EPIC] M18 · Platform Admin & Billing | F2: — | G2: Later | H2: L | I2: =IF(H2="S",0.5,IF(H2="M",1,IF(H2="L",2,0))) | J2: Later | K2: backend | L2: Accepted | N2: OPEN | O2: IDN-006 | P2: =IF(O2="",0,SUMPRODUCT(--ISNUMBER(SEARCH(", "&$A$2:$A$245&",",", "&O2&",")),--($L$2:$L$245<>"Done"))) | Q2: open
A3: ADM-L02 | B3: 206 | C3: [ADMIN] Meter usage for billing | D3: admin | E3: [EPIC] M18 · Platform Admin & Billing | F3: — | G3: Later | H3: M | I3: =IF(H3="S",0.5,IF(H3="M",1,IF(H3="L",2,0))) | J3: Later | K3: backend | L3: Accepted | N3: OPEN | O3: OBS-004 | P3: =IF(O3="",0,SUMPRODUCT(--ISNUMBER(SEARCH(", "&$A$2:$A$245&",",", "&O3&",")),--($L$2:$L$245<>"Done"))) | Q3: open
A4: ADM-L03 | B4: 207 | C4: [ADMIN] Add subscriptions and customer invoicing | D4: admin | E4: [EPIC] M18 · Platform Admin & Billing | F4: — | G4: Later | H4: L | I4: =IF(H4="S",0.5,IF(H4="M",1,IF(H4="L",2,0))) | J4: Later | K4: backend | L4: Accepted | N4: OPEN | O4: ADM-L02 | P4: =IF(O4="",0,SUMPRODUCT(--ISNUMBER(SEARCH(", "&$A$2:$A$245&",",", "&O4&",")),--($L$2:$L$245<>"Done"))) | Q4: open
A5: AGT-001 | B5: 132 | C5: [AGENT] Build the LLM adapter with routing and timeouts | D5: agent | E5: [EPIC] M09 · AI Agent | F5: P0 | G5: M1 | H5: M | I5: =IF(H5="S",0.5,IF(H5="M",1,IF(H5="L",2,0))) | J5: A | K5: ai | L5: Assigned | M5: therealtunguyen | N5: OPEN | O5: EXE-002 | P5: =IF(O5="",0,SUMPRODUCT(--ISNUMBER(SEARCH(", "&$A$2:$A$245&",",", "&O5&",")),--($L$2:$L$245<>"Done"))) | Q5: open
A6: AGT-002 | B6: 134 | C6: [AGENT] Log every AI call and fail closed | D6: agent | E6: [EPIC] M09 · AI Agent | F6: P0 | G6: M1 | H6: S | I6: =IF(H6="S",0.5,IF(H6="M",1,IF(H6="L",2,0))) | J6: A | K6: ai | L6: Assigned | M6: therealtunguyen | N6: OPEN | O6: AGT-001 | P6: =IF(O6="",0,SUMPRODUCT(--ISNUMBER(SEARCH(", "&$A$2:$A$245&",",", "&O6&",")),--($L$2:$L$245<>"Done"))) | Q6: open
A7: AGT-003 | B7: 133 | C7: [AGENT] Implement untrusted-content wrapping and sanitization | D7: agent | E7: [EPIC] M09 · AI Agent | F7: P0 | G7: M1 | H7: S | I7: =IF(H7="S",0.5,IF(H7="M",1,IF(H7="L",2,0))) | J7: A | K7: ai | L7: Assigned | M7: therealtunguyen | N7: OPEN | O7: AGT-001 | P7: =IF(O7="",0,SUMPRODUCT(--ISNUMBER(SEARCH(", "&$A$2:$A$245&",",", "&O7&",")),--($L$2:$L$245<>"Done"))) | Q7: open
A8: AGT-004 | B8: 135 | C8: [AGENT] Implement invoice extraction | D8: agent | E8: [EPIC] M09 · AI Agent | F8: P0 | G8: M1 | H8: M | I8: =IF(H8="S",0.5,IF(H8="M",1,IF(H8="L",2,0))) | J8: A | K8: ai | L8: Assigned | M8: therealtunguyen | N8: OPEN | O8: AGT-003, AGT-002, INV-004 | P8: =IF(O8="",0,SUMPRODUCT(--ISNUMBER(SEARCH(", "&$A$2:$A$245&",",", "&O8&",")),--($L$2:$L$245<>"Done"))) | Q8: open
A9: AGT-005 | B9: 170 | C9: [AGENT] Extract and validate payment terms | D9: agent | E9: [EPIC] M09 · AI Agent | F9: P0 | G9: M1 | H9: S | I9: =IF(H9="S",0.5,IF(H9="M",1,IF(H9="L",2,0))) | J9: A | K9: ai | L9: Assigned | M9: therealtunguyen | N9: OPEN | O9: AGT-004, ENG-005 | P9: =IF(O9="",0,SUMPRODUCT(--ISNUMBER(SEARCH(", "&$A$2:$A$245&",",", "&O9&",")),--($L$2:$L$245<>"Done"))) | Q9: open
A10: AGT-006 | B10: 171 | C10: [AGENT] Detect instruction-like text in documents | D10: agent | E10: [EPIC] M09 · AI Agent | F10: P0 | G10: M1 | H10: S | I10: =IF(H10="S",0.5,IF(H10="M",1,IF(H10="L",2,0))) | J10: A | K10: ai | L10: Assigned | M10: therealtunguyen | N10: OPEN | O10: AGT-004 | P10: =IF(O10="",0,SUMPRODUCT(--ISNUMBER(SEARCH(", "&$A$2:$A$245&",",", "&O10&",")),--($L$2:$L$245<>"Done"))) | Q10: open
A11: AGT-007 | B11: 143 | C11: [AGENT] Implement the read-only tool layer | D11: agent | E11: [EPIC] M09 · AI Agent | F11: P0 | G11: M1 | H11: M | I11: =IF(H11="S",0.5,IF(H11="M",1,IF(H11="L",2,0))) | J11: A | K11: ai | L11: Assigned | M11: therealtunguyen | N11: OPEN | O11: CHR-002, ENG-008, POL-003 | P11: =IF(O11="",0,SUMPRODUCT(--ISNUMBER(SEARCH(", "&$A$2:$A$245&",",", "&O11&",")),--($L$2:$L$245<>"Done"))) | Q11: open
A12: AGT-008 | B12: 144 | C12: [AGENT] Implement the plan proposer | D12: agent | E12: [EPIC] M09 · AI Agent | F12: P0 | G12: M1 | H12: M | I12: =IF(H12="S",0.5,IF(H12="M",1,IF(H12="L",2,0))) | J12: A | K12: ai | L12: Assigned | M12: therealtunguyen | N12: OPEN | O12: AGT-007 | P12: =IF(O12="",0,SUMPRODUCT(--ISNUMBER(SEARCH(", "&$A$2:$A$245&",",", "&O12&",")),--($L$2:$L$245<>"Done"))) | Q12: open
A13: AGT-009 | B13: 145 | C13: [AGENT] Score AI proposals and select the plan | D13: agent | E13: [EPIC] M09 · AI Agent | F13: P0 | G13: M1 | H13: S | I13: =IF(H13="S",0.5,IF(H13="M",1,IF(H13="L",2,0))) | J13: A | K13: ai | L13: Assigned | M13: therealtunguyen | N13: OPEN | O13: AGT-008, ENG-008 | P13: =IF(O13="",0,SUMPRODUCT(--ISNUMBER(SEARCH(", "&$A$2:$A$245&",",", "&O13&",")),--($L$2:$L$245<>"Done"))) | Q13: open
A14: AGT-010 | B14: 172 | C14: [AGENT] Implement rule-based fallback templates | D14: agent | E14: [EPIC] M09 · AI Agent | F14: P0 | G14: M1 | H14: S | I14: =IF(H14="S",0.5,IF(H14="M",1,IF(H14="L",2,0))) | J14: A | K14: ai | L14: Assigned | M14: therealtunguyen | N14: OPEN | O14: ENG-007, POL-003 | P14: =IF(O14="",0,SUMPRODUCT(--ISNUMBER(SEARCH(", "&$A$2:$A$245&",",", "&O14&",")),--($L$2:$L$245<>"Done"))) | Q14: open
A15: AGT-011 | B15: 173 | C15: [AGENT] Draft exception requests with a numeric post-check | D15: agent | E15: [EPIC] M09 · AI Agent | F15: P1 | G15: M1 | H15: S | I15: =IF(H15="S",0.5,IF(H15="M",1,IF(H15="L",2,0))) | J15: B | K15: ai | L15: Assigned | M15: therealtunguyen | N15: OPEN | O15: AGT-001, MDT-006 | P15: =IF(O15="",0,SUMPRODUCT(--ISNUMBER(SEARCH(", "&$A$2:$A$245&",",", "&O15&",")),--($L$2:$L$245<>"Done"))) | Q15: open
A16: AGT-012 | B16: 174 | C16: [AGENT] Build the Copilot backend | D16: agent | E16: [EPIC] M09 · AI Agent | F16: P1 | G16: M1 | H16: L | I16: =IF(H16="S",0.5,IF(H16="M",1,IF(H16="L",2,0))) | J16: After submission | K16: ai | L16: Assigned | M16: therealtunguyen | N16: OPEN | O16: AGT-007 | P16: =IF(O16="",0,SUMPRODUCT(--ISNUMBER(SEARCH(", "&$A$2:$A$245&",",", "&O16&",")),--($L$2:$L$245<>"Done"))) | Q16: open
... A25: AUD-004 | B25: 198 | C25: [AUDIT] Propagate coverage labels through the API | D25: audit | E25: [EPIC] M15 · Audit & Evidence | F25: P1 | G25: M1 | H25: S | I25: =IF(H25="S",0.5,IF(H25="M",1,IF(H25="L",2,0))) | J25: After submission | K25: backend | L25: Assigned | M25: Nostidus4 | N25: OPEN | O25: CHR-002 | P25: =IF(O25="",0,SUMPRODUCT(--ISNUMBER(SEARCH(", "&$A$2:$A$245&",",", "&O25&",")),--($L$2:$L$245<>"Done"))) | Q25: open
A26: AUD-L01 | B26: 199 | C26: [AUDIT] Anchor the audit hash root on-chain daily | D26: audit | E26: [EPIC] M15 · Audit & Evidence | F26: — | G26: Later | H26: S | I26: =IF(H26="S",0.5,IF(H26="M",1,IF(H26="L",2,0))) | J26: Later | K26: backend | L26: Accepted | N26: OPEN | O26: AUD-002 | P26: =IF(O26="",0,SUMPRODUCT(--ISNUMBER(SEARCH(", "&$A$2:$A$245&",",", "&O26&",")),--($L$2:$L$245<>"Done"))) | Q26: open
A27: CHR-001 | B27: 35 | C27: [CHAIN] Build the RPC client with failover | D27: chain-reader | E27: [EPIC] M06 · Chain Reader & Tx Tracking | F27: P0 | G27: M1 | H27: M | I27: =IF(H27="S",0.5,IF(H27="M",1,IF(H27="L",2,0))) | J27: A | K27: backend | L27: Assigned | M27: Nostidus4 | N27: OPEN | O27: TRS-002 | P27: =IF(O27="",0,SUMPRODUCT(--ISNUMBER(SEARCH(", "&$A$2:$A$245&",",", "&O27&",")),--($L$2:$L$245<>"Done"))) | Q27: open
A28: CHR-002 | B28: 140 | C28: [CHAIN] Implement block-consistent snapshots | D28: chain-reader | E28: [EPIC] M06 · Chain Reader & Tx Tracking | F28: P0 | G28: M1 | H28: M | I28: =IF(H28="S",0.5,IF(H28="M",1,IF(H28="L",2,0))) | J28: A | K28: backend | L28: Assigned | M28: Nostidus4 | N28: OPEN | O28: CHR-001, TRS-004 | P28: =IF(O28="",0,SUMPRODUCT(--ISNUMBER(SEARCH(", "&$A$2:$A$245&",",", "&O28&",")),--($L$2:$L$245<>"Done"))) | Q28: open
A29: CHR-003 | B29: 47 | C29: [CHAIN] Implement the transaction tracker | D29: chain-reader | E29: [EPIC] M06 · Chain Reader & Tx Tracking | F29: P0 | G29: M1 | H29: M | I29: =IF(H29="S",0.5,IF(H29="M",1,IF(H29="L",2,0))) | J29: A | K29: backend | L29: Assigned | M29: Nostidus4 | N29: OPEN | O29: CHR-001, EXE-001 | P29: =IF(O29="",0,SUMPRODUCT(--ISNUMBER(SEARCH(", "&$A$2:$A$245&",",", "&O29&",")),--($L$2:$L$245<>"Done"))) | Q29: open
A30: CHR-004 | B30: 141 | C30: [CHAIN] Detect reorgs and re-evaluate status | D30: chain-reader | E30: [EPIC] M06 · Chain Reader & Tx Tracking | F30: P1 | G30: M1 | H30: S | I30: =IF(H30="S",0.5,IF(H30="M",1,IF(H30="L",2,0))) | J30: After submission | K30: backend | L30: Assigned | M30: Nostidus4 | N30: OPEN | O30: CHR-003 | P30: =IF(O30="",0,SUMPRODUCT(--ISNUMBER(SEARCH(", "&$A$2:$A$245&",",", "&O30&",")),--($L$2:$L$245<>"Done"))) | Q30: open
A31: CHR-005 | B31: 117 | C31: [CHAIN] Index module and Safe events | D31: chain-reader | E31: [EPIC] M06 · Chain Reader & Tx Tracking | F31: P1 | G31: M1 | H31: M | I31: =IF(H31="S",0.5,IF(H31="M",1,IF(H31="L",2,0))) | J31: A | K31: backend | L31: Assigned | M31: Nostidus4 | N31: OPEN | O31: CHR-001, SC-016 | P31: =IF(O31="",0,SUMPRODUCT(--ISNUMBER(SEARCH(", "&$A$2:$A$245&",",", "&O31&",")),--($L$2:$L$245<>"Done"))) | Q31: open
A32: CHR-006 | B32: 253 | C32: [CHAIN] Index treasury token movements and alert on unexpected outflows | D32: chain-reader | E32: [EPIC] M06 · Chain Reader & Tx Tracking | F32: P0 | G32: M1 | H32: S | I32: =IF(H32="S",0.5,IF(H32="M",1,IF(H32="L",2,0))) | J32: A | K32: backend | L32: Assigned | M32: Nostidus4 | N32: OPEN | O32: CHR-005, EXE-001 | P32: =IF(O32="",0,SUMPRODUCT(--ISNUMBER(SEARCH(", "&$A$2:$A$245&",",", "&O32&",")),--($L$2:$L$245<>"Done"))) | Q32: open
A33: CMP-001 | B33: 50 | C33: [COMPLIANCE] Build the screening adapter and fixture provider | D33: compliance | E33: [EPIC] M14 · Compliance | F33: P1 | G33: M1 | H33: S | I33: =IF(H33="S",0.5,IF(H33="M",1,IF(H33="L",2,0))) | J33: A | K33: backend | L33: Assigned | M33: Nostidus4 | N33: OPEN | O33: MDT-001 | P33: =IF(O33="",0,SUMPRODUCT(--ISNUMBER(SEARCH(", "&$A$2:$A$245&",",", "&O33&",")),--($L$2:$L$245<>"Done"))) | Q33: open
A34: CMP-002 | B34: 191 | C34: [COMPLIANCE] Screen payees before each PAY | D34: compliance | E34: [EPIC] M14 · Compliance | F34: P1 | G34: M1 | H34: S | I34: =IF(H34="S",0.5,IF(H34="M",1,IF(H34="L",2,0))) | J34: After submission | K34: backend | L34: Assigned | M34: Nostidus4 | N34: OPEN | O34: CMP-001, POL-003 | P34: =IF(O34="",0,SUMPRODUCT(--ISNUMBER(SEARCH(", "&$A$2:$A$245&",",", "&O34&",")),--($L$2:$L$245<>"Done"))) | Q34: open
A35: CMP-003 | B35: 192 | C35: [COMPLIANCE] Implement data classification, encryption helpers and log redaction | D35: compliance | E35: [EPIC] M14 · Compliance | F35: P0 | G35: M1 | H35: M | I35: =IF(H35="S",0.5,IF(H35="M",1,IF(H35="L",2,0))) | J35: B | K35: backend | L35: Assigned | M35: Nostidus4 | N35: OPEN | O35: DEV-001 | P35: =IF(O35="",0,SUMPRODUCT(--ISNUMBER(SEARCH(", "&$A$2:$A$245&",",", "&O35&",")),--($L$2:$L$245<>"Done"))) | Q35: open
A36: CMP-L01 | B36: 193 | C36: [COMPLIANCE] Integrate a KYB provider | D36: compliance | E36: [EPIC] M14 · Compliance | F36: — | G36: Later | H36: L | I36: =IF(H36="S",0.5,IF(H36="M",1,IF(H36="L",2,0))) | J36: Later | K36: backend | L36: Accepted | N36: OPEN | O36: CMP-001 | P36: =IF(O36="",0,SUMPRODUCT(--ISNUMBER(SEARCH(", "&$A$2:$A$245&",",", "&O36&",")),--($L$2:$L$245<>"Done"))) | Q36: open
A37: CMP-L02 | B37: 194 | C37: [COMPLIANCE] Add Travel Rule support | D37: compliance | E37: [EPIC] M14 · Compliance | F37: — | G37: Later | H37: L | I37: =IF(H37="S",0.5,IF(H37="M",1,IF(H37="L",2,0))) | J37: Later | K37: backend | L37: Accepted | N37: OPEN | O37: CMP-L01 | P37: =IF(O37="",0,SUMPRODUCT(--ISNUMBER(SEARCH(", "&$A$2:$A$245&",",", "&O37&",")),--($L$2:$L$245<>"Done"))) | Q37: open
A38: CMP-L03 | B38: 195 | C38: [COMPLIANCE] Add retention and deletion workflows | D38: compliance | E38: [EPIC] M14 · Compliance | F38: — | G38: Later | H38: M | I38: =IF(H38="S",0.5,IF(H38="M",1,IF(H38="L",2,0))) | J38: Later | K38: backend | L38: Accepted | N38: OPEN | O38: CMP-003 | P38: =IF(O38="",0,SUMPRODUCT(--ISNUMBER(SEARCH(", "&$A$2:$A$245&",",", "&O38&",")),--($L$2:$L$245<>"Done"))) | Q38: open
A39: CMP-L04 | B39: 196 | C39: [COMPLIANCE] Add region pinning for stored data | D39: compliance | E39: [EPIC] M14 · Compliance | F39: — | G39: Later | H39: M | I39: =IF(H39="S",0.5,IF(H39="M",1,IF(H39="L",2,0))) | J39: Later | K39: backend | L39: Accepted | N39: OPEN | O39: CMP-L03 | P39: =IF(O39="",0,SUMPRODUCT(--ISNUMBER(SEARCH(", "&$A$2:$A$245&",",", "&O39&",")),--($L$2:$L$245<>"Done"))) | Q39: open
A40: DEV-001 | B40: 21 | C40: [DEVEX] Initialize monorepo skeleton | D40: devex | E40: [EPIC] M19 · Developer Experience & Quality | F40: P0 | G40: M1 | H40: M | I40: =IF(H40="S",0.5,IF(H40="M",1,IF(H40="L",2,0))) | J40: A | K40: infrastructure | L40: Done | N40: CLOSED | P40: =IF(O40="",0,SUMPRODUCT(--ISNUMBER(SEARCH(", "&$A$2:$A$245&",",", "&O40&",")),--($L$2:$L$245<>"Done"))) | Q40: open
A41: DEV-002 | B41: 22 | C41: [DEVEX] Create Docker Compose stack (local profile) | D41: devex | E41: [EPIC] M19 · Developer Experience & Quality | F41: P0 | G41: M1 | H41: M | I41: =IF(H41="S",0.5,IF(H41="M",1,IF(H41="L",2,0))) | J41: A | K41: infrastructure | L41: Done | N41: CLOSED | O41: DEV-001 | P41: =IF(O41="",0,SUMPRODUCT(--ISNUMBER(SEARCH(", "&$A$2:$A$245&",",", "&O41&",")),--($L$2:$L$245<>"Done"))) | Q41: open
A42: DEV-003 | B42: 23 | C42: [DEVEX] Add CI workflow for Python | D42: devex | E42: [EPIC] M19 · Developer Experience & Quality | F42: P1 | G42: M1 | H42: S | I42: =IF(H42="S",0.5,IF(H42="M",1,IF(H42="L",2,0))) | J42: A | K42: infrastructure | L42: Done | N42: CLOSED | O42: DEV-001 | P42: =IF(O42="",0,SUMPRODUCT(--ISNUMBER(SEARCH(", "&$A$2:$A$245&",",", "&O42&",")),--($L$2:$L$245<>"Done"))) | Q42: open
A43: DEV-004 | B43: 25 | C43: [DEVEX] Add CI workflow for contracts | D43: devex | E43: [EPIC] M19 · Developer Experience & Quality | F43: P1 | G43: M1 | H43: S | I43: =IF(H43="S",0.5,IF(H43="M",1,IF(H43="L",2,0))) | J43: B | K43: infrastructure | L43: Assigned | M43: therealtunguyen | N43: OPEN | O43: SC-001 | P43: =IF(O43="",0,SUMPRODUCT(--ISNUMBER(SEARCH(", "&$A$2:$A$245&",",", "&O43&",")),--($L$2:$L$245<>"Done"))) | Q43: open
A44: DEV-005 | B44: 27 | C44: [DEVEX] Add CI workflow for web and OpenAPI client drift | D44: devex | E44: [EPIC] M19 · Developer Experience & Quality | F44: P1 | G44: M1 | H44: S | I44: =IF(H44="S",0.5,IF(H44="M",1,IF(H44="L",2,0))) | J44: After submission | K44: infrastructure | L44: Done | N44: CLOSED | O44: WEB-001 | P44: =IF(O44="",0,SUMPRODUCT(--ISNUMBER(SEARCH(", "&$A$2:$A$245&",",", "&O44&",")),--($L$2:$L$245<>"Done"))) | Q44: open
A45: DEV-006 | B45: 53 | C45: [DEVEX] Write seed script for the local environment | D45: devex | E45: [EPIC] M19 · Developer Experience & Quality | F45: P1 | G45: M1 | H45: M | I45: =IF(H45="S",0.5,IF(H45="M",1,IF(H45="L",2,0))) | J45: A | K45: infrastructure | L45: Assigned | M45: therealtunguyen | N45: OPEN | O45: SC-016, TRS-004, MDT-003, INV-003 | P45: =IF(O45="",0,SUMPRODUCT(--ISNUMBER(SEARCH(", "&$A$2:$A$245&",",", "&O45&",")),--($L$2:$L$245<>"Done"))) | Q45: open
A46: DEV-007 | B46: 67 | C46: [DEVEX] Build scenario runner CLI | D46: devex | E46: [EPIC] M19 · Developer Experience & Quality | F46: P1 | G46: M1 | H46: M | I46: =IF(H46="S",0.5,IF(H46="M",1,IF(H46="L",2,0))) | J46: A | K46: infrastructure | L46: Assigned | M46: therealtunguyen | N46: OPEN | O46: DEV-006, AUD-003 | P46: =IF(O46="",0,SUMPRODUCT(--ISNUMBER(SEARCH(", "&$A$2:$A$245&",",", "&O46&",")),--($L$2:$L$245<>"Done"))) | Q46: open
A47: DEV-008 | B47: 68 | C47: [DEVEX] Write the demo runbook | D47: devex | E47: [EPIC] M19 · Developer Experience & Quality | F47: P1 | G47: M1 | H47: S | I47: =IF(H47="S",0.5,IF(H47="M",1,IF(H47="L",2,0))) | J47: A | K47: infrastructure | L47: Assigned | M47: therealtunguyen | N47: OPEN | O47: DEV-007 | P47: =IF(O47="",0,SUMPRODUCT(--ISNUMBER(SEARCH(", "&$A$2:$A$245&",",", "&O47&",")),--($L$2:$L$245<>"Done"))) | Q47: open
A48: DEV-009 | B48: 69 | C48: [DEVEX] Build the reliability run harness | D48: devex | E48: [EPIC] M19 · Developer Experience & Quality | F48: P1 | G48: M1 | H48: S | I48: =IF(H48="S",0.5,IF(H48="M",1,IF(H48="L",2,0))) | J48: After submission | K48: infrastructure | L48: Assigned | M48: therealtunguyen | N48: OPEN | O48: DEV-007 | P48: =IF(O48="",0,SUMPRODUCT(--ISNUMBER(SEARCH(", "&$A$2:$A$245&",",", "&O48&",")),--($L$2:$L$245<>"Done"))) | Q48: open
A49: DEV-010 | B49: 71 | C49: [DEVEX] Add testnet profile and VM deployment | D49: devex | E49: [EPIC] M19 · Developer Experience & Quality | F49: P1 | G49: M1 | H49: M | I49: =IF(H49="S",0.5,IF(H49="M",1,IF(H49="L",2,0))) | J49: A | K49: infrastructure | L49: Assigned | M49: therealtunguyen | N49: OPEN | O49: DEV-002, DOM-001, SC-016 | P49: =IF(O49="",0,SUMPRODUCT(--ISNUMBER(SEARCH(", "&$A$2:$A$245&",",", "&O49&",")),--($L$2:$L$245<>"Done"))) | Q49: open
A50: DEV-011 | B50: 72 | C50: [DEVEX] Enforce module boundaries with import-linter | D50: devex | E50: [EPIC] M19 · Developer Experience & Quality | F50: P1 | G50: M1 | H50: S | I50: =IF(H50="S",0.5,IF(H50="M",1,IF(H50="L",2,0))) | J50: After submission | K50: infrastructure | L50: Done | N50: CLOSED | O50: DEV-001 | P50: =IF(O50="",0,SUMPRODUCT(--ISNUMBER(SEARCH(", "&$A$2:$A$245&",",", "&O50&",")),--($L$2:$L$245<>"Done"))) | Q50: open
A51: DEV-012 | B51: 264 | C51: [DEVEX] Add the deployment config gate to CI | D51: devex | E51: [EPIC] M19 · Developer Experience & Quality | F51: P0 | G51: M1 | H51: S | I51: =IF(H51="S",0.5,IF(H51="M",1,IF(H51="L",2,0))) | J51: A | K51: infrastructure | L51: Assigned | M51: therealtunguyen | N51: OPEN | O51: SC-016, DEV-003 | P51: =IF(O51="",0,SUMPRODUCT(--ISNUMBER(SEARCH(", "&$A$2:$A$245&",",", "&O51&",")),--($L$2:$L$245<>"Done"))) | Q51: open
A52: DOM-001 | B52: 70 | C52: [DOMAIN] Verify Ethereum Sepolia infrastructure (owner: Phúc) | D52: domain-evidence | E52: [EPIC] M20 · Domain & Evidence (non-code) | F52: P0 | G52: M1 | H52: S | I52: =IF(H52="S",0.5,IF(H52="M",1,IF(H52="L",2,0))) | J52: A | K52: non-code | L52: Ready for Assignment | N52: OPEN | P52: =IF(O52="",0,SUMPRODUCT(--ISNUMBER(SEARCH(", "&$A$2:$A$245&",",", "&O52&",")),--($L$2:$L$245<>"Done"))) | Q52: open
A53: DOM-002 | B53: 230 | C53: [DOMAIN] Set up tUSDC and the Circle USDC evidence run (owner: Phúc) | D53: domain-evidence | E53: [EPIC] M20 · Domain & Evidence (non-code) | F53: P0 | G53: M1 | H53: S | I53: =IF(H53="S",0.5,IF(H53="M",1,IF(H53="L",2,0))) | J53: A | K53: non-code | L53: Ready for Assignment | N53: OPEN | O53: DOM-001 | P53: =IF(O53="",0,SUMPRODUCT(--ISNUMBER(SEARCH(", "&$A$2:$A$245&",",", "&O53&",")),--($L$2:$L$245<>"Done"))) | Q53: open
A54: DOM-003 | B54: 231 | C54: [DOMAIN] Ask the organizers whether testnet evidence is accepted | D54: domain-evidence | E54: [EPIC] M20 · Domain & Evidence (non-code) | F54: P1 | G54: M1 | H54: S | I54: =IF(H54="S",0.5,IF(H54="M",1,IF(H54="L",2,0))) | J54: A | K54: non-code | L54: Ready for Assignment | N54: OPEN | P54: =IF(O54="",0,SUMPRODUCT(--ISNUMBER(SEARCH(", "&$A$2:$A$245&",",", "&O54&",")),--($L$2:$L$245<>"Done"))) | Q54: open
A55: DOM-004 | B55: 175 | C55: [DOMAIN] Author the labelled invoice dataset (30) | D55: domain-evidence | E55: [EPIC] M20 · Domain & Evidence (non-code) | F55: P0 | G55: M1 | H55: M | I55: =IF(H55="S",0.5,IF(H55="M",1,IF(H55="L",2,0))) | J55: B | K55: non-code | L55: Ready for Assignment | N55: OPEN | P55: =IF(O55="",0,SUMPRODUCT(--ISNUMBER(SEARCH(", "&$A$2:$A$245&",",", "&O55&",")),--($L$2:$L$245<>"Done"))) | Q55: open
A56: DOM-005 | B56: 177 | C56: [DOMAIN] Author planner scenarios with ground truth (≥30) | D56: domain-evidence | E56: [EPIC] M20 · Domain & Evidence (non-code) | F56: P0 | G56: M1 | H56: L | I56: =IF(H56="S",0.5,IF(H56="M",1,IF(H56="L",2,0))) | J56: A | K56: non-code | L56: Ready for Assignment | N56: OPEN | P56: =IF(O56="",0,SUMPRODUCT(--ISNUMBER(SEARCH(", "&$A$2:$A$245&",",", "&O56&",")),--($L$2:$L$245<>"Done"))) | Q56: open
A57: DOM-006 | B57: 179 | C57: [DOMAIN] Author the red-team invoice set (20) | D57: domain-evidence | E57: [EPIC] M20 · Domain & Evidence (non-code) | F57: P0 | G57: M1 | H57: M | I57: =IF(H57="S",0.5,IF(H57="M",1,IF(H57="L",2,0))) | J57: A | K57: non-code | L57: Ready for Assignment | N57: OPEN | P57: =IF(O57="",0,SUMPRODUCT(--ISNUMBER(SEARCH(", "&$A$2:$A$245&",",", "&O57&",")),--($L$2:$L$245<>"Done"))) | Q57: open
A58: DOM-007 | B58: 181 | C58: [DOMAIN] Author Copilot question cases (20) | D58: domain-evidence | E58: [EPIC] M20 · Domain & Evidence (non-code) | F58: P1 | G58: M1 | H58: S | I58: =IF(H58="S",0.5,IF(H58="M",1,IF(H58="L",2,0))) | J58: After submission | K58: non-code | L58: Ready for Assignment | N58: OPEN | O58: DOM-005 | P58: =IF(O58="",0,SUMPRODUCT(--ISNUMBER(SEARCH(", "&$A$2:$A$245&",",", "&O58&",")),--($L$2:$L$245<>"Done"))) | Q58: open
A59: DOM-008 | B59: 232 | C59: [DOMAIN] Review business rules and demo limits from a finance view | D59: domain-evidence | E59: [EPIC] M20 · Domain & Evidence (non-code) | F59: P0 | G59: M1 | H59: S | I59: =IF(H59="S",0.5,IF(H59="M",1,IF(H59="L",2,0))) | J59: A | K59: non-code | L59: Ready for Assignment | N59: OPEN | P59: =IF(O59="",0,SUMPRODUCT(--ISNUMBER(SEARCH(", "&$A$2:$A$245&",",", "&O59&",")),--($L$2:$L$245<>"Done"))) | Q59: open
A60: DOM-009 | B60: 233 | C60: [DOMAIN] Review the threat model and write the known-risk list | D60: domain-evidence | E60: [EPIC] M20 · Domain & Evidence (non-code) | F60: P0 | G60: M1 | H60: M | I60: =IF(H60="S",0.5,IF(H60="M",1,IF(H60="L",2,0))) | J60: A | K60: non-code | L60: Ready for Assignment | N60: OPEN | P60: =IF(O60="",0,SUMPRODUCT(--ISNUMBER(SEARCH(", "&$A$2:$A$245&",",", "&O60&",")),--($L$2:$L$245<>"Done"))) | Q60: open
A61: DOM-010 | B61: 234 | C61: [DOMAIN] Run customer interviews (2–3) | D61: domain-evidence | E61: [EPIC] M20 · Domain & Evidence (non-code) | F61: P1 | G61: M1 | H61: M | I61: =IF(H61="S",0.5,IF(H61="M",1,IF(H61="L",2,0))) | J61: B | K61: non-code | L61: Ready for Assignment | N61: OPEN | P61: =IF(O61="",0,SUMPRODUCT(--ISNUMBER(SEARCH(", "&$A$2:$A$245&",",", "&O61&",")),--($L$2:$L$245<>"Done"))) | Q61: open
A62: DOM-011 | B62: 235 | C62: [DOMAIN] Write the security self-assessment report | D62: domain-evidence | E62: [EPIC] M20 · Domain & Evidence (non-code) | F62: P0 | G62: M1 | H62: M | I62: =IF(H62="S",0.5,IF(H62="M",1,IF(H62="L",2,0))) | J62: A | K62: non-code | L62: Ready for Assignment | N62: OPEN | O62: DOM-009, SC-015 | P62: =IF(O62="",0,SUMPRODUCT(--ISNUMBER(SEARCH(", "&$A$2:$A$245&",",", "&O62&",")),--($L$2:$L$245<>"Done"))) | Q62: open
A63: DOM-012 | B63: 236 | C63: [DOMAIN] Assemble the technical documentation for submission | D63: domain-evidence | E63: [EPIC] M20 · Domain & Evidence (non-code) | F63: P0 | G63: M1 | H63: M | I63: =IF(H63="S",0.5,IF(H63="M",1,IF(H63="L",2,0))) | J63: A | K63: non-code | L63: Ready for Assignment | N63: OPEN | O63: DOM-011 | P63: =IF(O63="",0,SUMPRODUCT(--ISNUMBER(SEARCH(", "&$A$2:$A$245&",",", "&O63&",")),--($L$2:$L$245<>"Done"))) | Q63: open
A64: DOM-013 | B64: 237 | C64: [DOMAIN] Create the 10-minute presentation deck | D64: domain-evidence | E64: [EPIC] M20 · Domain & Evidence (non-code) | F64: P0 | G64: M1 | H64: M | I64: =IF(H64="S",0.5,IF(H64="M",1,IF(H64="L",2,0))) | J64: A | K64: non-code | L64: Ready for Assignment | N64: OPEN | O64: DOM-008 | P64: =IF(O64="",0,SUMPRODUCT(--ISNUMBER(SEARCH(", "&$A$2:$A$245&",",", "&O64&",")),--($L$2:$L$245<>"Done"))) | Q64: open
A65: DOM-014 | B65: 238 | C65: [DOMAIN] Script and record the 5-minute demo video | D65: domain-evidence | E65: [EPIC] M20 · Domain & Evidence (non-code) | F65: P0 | G65: M1 | H65: M | I65: =IF(H65="S",0.5,IF(H65="M",1,IF(H65="L",2,0))) | J65: A | K65: non-code | L65: Ready for Assignment | N65: OPEN | O65: DEV-008 | P65: =IF(O65="",0,SUMPRODUCT(--ISNUMBER(SEARCH(", "&$A$2:$A$245&",",", "&O65&",")),--($L$2:$L$245<>"Done"))) | Q65: open
A66: DOM-015 | B66: 239 | C66: [DOMAIN] Write the compliance positioning note and license inventory | D66: domain-evidence | E66: [EPIC] M20 · Domain & Evidence (non-code) | F66: P1 | G66: M1 | H66: S | I66: =IF(H66="S",0.5,IF(H66="M",1,IF(H66="L",2,0))) | J66: B | K66: non-code | L66: Ready for Assignment | N66: OPEN | P66: =IF(O66="",0,SUMPRODUCT(--ISNUMBER(SEARCH(", "&$A$2:$A$245&",",", "&O66&",")),--($L$2:$L$245<>"Done"))) | Q66: open
A67: DOM-016 | B67: 240 | C67: [DOMAIN] Update the FigJam board from the repo diagrams | D67: domain-evidence | E67: [EPIC] M20 · Domain & Evidence (non-code) | F67: P2 | G67: M1 | H67: S | I67: =IF(H67="S",0.5,IF(H67="M",1,IF(H67="L",2,0))) | J67: After submission | K67: non-code | L67: Ready for Assignment | N67: OPEN | P67: =IF(O67="",0,SUMPRODUCT(--ISNUMBER(SEARCH(", "&$A$2:$A$245&",",", "&O67&",")),--($L$2:$L$245<>"Done"))) | Q67: open
A68: DOM-017 | B68: 241 | C68: [DOMAIN] Choose the repository license | D68: domain-evidence | E68: [EPIC] M20 · Domain & Evidence (non-code) | F68: P1 | G68: M1 | H68: S | I68: =IF(H68="S",0.5,IF(H68="M",1,IF(H68="L",2,0))) | J68: After submission | K68: non-code | L68: Ready for Assignment | N68: OPEN | P68: =IF(O68="",0,SUMPRODUCT(--ISNUMBER(SEARCH(", "&$A$2:$A$245&",",", "&O68&",")),--($L$2:$L$245<>"Done"))) | Q68: open
A69: ENG-001 | B69: 42 | C69: [ENGINE] Create py-core money types and domain models | D69: financial-engine | E69: [EPIC] M07 · Financial Engine (py-core) | F69: P0 | G69: M1 | H69: M | I69: =IF(H69="S",0.5,IF(H69="M",1,IF(H69="L",2,0))) | J69: A | K69: backend | L69: Assigned | M69: Nostidus4 | N69: OPEN | O69: DEV-001 | P69: =IF(O69="",0,SUMPRODUCT(--ISNUMBER(SEARCH(", "&$A$2:$A$245&",",", "&O69&",")),--($L$2:$L$245<>"Done"))) | Q69: open
A70: ENG-002 | B70: 92 | C70: [ENGINE] Implement the liquidity calculator | D70: financial-engine | E70: [EPIC] M07 · Financial Engine (py-core) | F70: P0 | G70: M1 | H70: M | I70: =IF(H70="S",0.5,IF(H70="M",1,IF(H70="L",2,0))) | J70: A | K70: backend | L70: Assigned | M70: Nostidus4 | N70: OPEN | O70: ENG-001 | P70: =IF(O70="",0,SUMPRODUCT(--ISNUMBER(SEARCH(", "&$A$2:$A$245&",",", "&O70&",")),--($L$2:$L$245<>"Done"))) | Q70: open
A71: ENG-003 | B71: 93 | C71: [ENGINE] Implement the refill decision table | D71: financial-engine | E71: [EPIC] M07 · Financial Engine (py-core) | F71: P0 | G71: M1 | H71: S | I71: =IF(H71="S",0.5,IF(H71="M",1,IF(H71="L",2,0))) | J71: A | K71: backend | L71: Assigned | M71: Nostidus4 | N71: OPEN | O71: ENG-002 | P71: =IF(O71="",0,SUMPRODUCT(--ISNUMBER(SEARCH(", "&$A$2:$A$245&",",", "&O71&",")),--($L$2:$L$245<>"Done"))) | Q71: open
A72: ENG-004 | B72: 94 | C72: [ENGINE] Add property tests for buffer and limit safety | D72: financial-engine | E72: [EPIC] M07 · Financial Engine (py-core) | F72: P0 | G72: M1 | H72: S | I72: =IF(H72="S",0.5,IF(H72="M",1,IF(H72="L",2,0))) | J72: After submission | K72: backend | L72: Assigned | M72: Nostidus4 | N72: OPEN | O72: ENG-003 | P72: =IF(O72="",0,SUMPRODUCT(--ISNUMBER(SEARCH(", "&$A$2:$A$245&",",", "&O72&",")),--($L$2:$L$245<>"Done"))) | Q72: open
A73: ENG-005 | B73: 95 | C73: [ENGINE] Model payment terms and their value function | D73: financial-engine | E73: [EPIC] M07 · Financial Engine (py-core) | F73: P0 | G73: M1 | H73: S | I73: =IF(H73="S",0.5,IF(H73="M",1,IF(H73="L",2,0))) | J73: A | K73: backend | L73: Assigned | M73: Nostidus4 | N73: OPEN | O73: ENG-001 | P73: =IF(O73="",0,SUMPRODUCT(--ISNUMBER(SEARCH(", "&$A$2:$A$245&",",", "&O73&",")),--($L$2:$L$245<>"Done"))) | Q73: open
A74: ENG-006 | B74: 96 | C74: [ENGINE] Implement the baseline scheduler B1 (earliest deadline first) | D74: financial-engine | E74: [EPIC] M07 · Financial Engine (py-core) | F74: P0 | G74: M1 | H74: S | I74: =IF(H74="S",0.5,IF(H74="M",1,IF(H74="L",2,0))) | J74: A | K74: backend | L74: Assigned | M74: Nostidus4 | N74: OPEN | O74: ENG-003, ENG-005 | P74: =IF(O74="",0,SUMPRODUCT(--ISNUMBER(SEARCH(", "&$A$2:$A$245&",",", "&O74&",")),--($L$2:$L$245<>"Done"))) | Q74: open
A75: ENG-007 | B75: 97 | C75: [ENGINE] Implement the terms-aware scheduler with OR-Tools CP-SAT | D75: financial-engine | E75: [EPIC] M07 · Financial Engine (py-core) | F75: P0 | G75: M1 | H75: L | I75: =IF(H75="S",0.5,IF(H75="M",1,IF(H75="L",2,0))) | J75: A | K75: backend | L75: Assigned | M75: Nostidus4 | N75: OPEN | O75: ENG-006, ENG-012 | P75: =IF(O75="",0,SUMPRODUCT(--ISNUMBER(SEARCH(", "&$A$2:$A$245&",",", "&O75&",")),--($L$2:$L$245<>"Done"))) | Q75: open
A76: ENG-008 | B76: 98 | C76: [ENGINE] Expose plan scoring and binding-constraint reporting | D76: financial-engine | E76: [EPIC] M07 · Financial Engine (py-core) | F76: P0 | G76: M1 | H76: S | I76: =IF(H76="S",0.5,IF(H76="M",1,IF(H76="L",2,0))) | J76: A | K76: backend | L76: Assigned | M76: Nostidus4 | N76: OPEN | O76: ENG-007 | P76: =IF(O76="",0,SUMPRODUCT(--ISNUMBER(SEARCH(", "&$A$2:$A$245&",",", "&O76&",")),--($L$2:$L$245<>"Done"))) | Q76: open
A77: ENG-009 | B77: 99 | C77: [ENGINE] Implement invoice fingerprint normalization and hashing | D77: financial-engine | E77: [EPIC] M07 · Financial Engine (py-core) | F77: P0 | G77: M1 | H77: S | I77: =IF(H77="S",0.5,IF(H77="M",1,IF(H77="L",2,0))) | J77: A | K77: backend | L77: Assigned | M77: Nostidus4 | N77: OPEN | O77: ENG-001 | P77: =IF(O77="",0,SUMPRODUCT(--ISNUMBER(SEARCH(", "&$A$2:$A$245&",",", "&O77&",")),--($L$2:$L$245<>"Done"))) | Q77: open
A78: ENG-010 | B78: 57 | C78: [ENGINE] Build EIP-712 typed data for payment approvals and attestations | D78: financial-engine | E78: [EPIC] M07 · Financial Engine (py-core) | F78: P0 | G78: M1 | H78: M | I78: =IF(H78="S",0.5,IF(H78="M",1,IF(H78="L",2,0))) | J78: A | K78: backend | L78: Assigned | M78: Nostidus4 | N78: OPEN | O78: SC-017, ENG-001 | P78: =IF(O78="",0,SUMPRODUCT(--ISNUMBER(SEARCH(", "&$A$2:$A$245&",",", "&O78&",")),--($L$2:$L$245<>"Done"))) | Q78: open
A79: ENG-011 | B79: 100 | C79: [ENGINE] Implement the 7-day liquidity forecast | D79: financial-engine | E79: [EPIC] M07 · Financial Engine (py-core) | F79: P2 | G79: M1 | H79: S | I79: =IF(H79="S",0.5,IF(H79="M",1,IF(H79="L",2,0))) | J79: After submission | K79: backend | L79: Assigned | M79: Nostidus4 | N79: OPEN | O79: ENG-003 | P79: =IF(O79="",0,SUMPRODUCT(--ISNUMBER(SEARCH(", "&$A$2:$A$245&",",", "&O79&",")),--($L$2:$L$245<>"Done"))) | Q79: open
A80: ENG-012 | B80: 243 | C80: [ENGINE] Implement the exhaustive oracle scheduler for tests | D80: financial-engine | E80: [EPIC] M07 · Financial Engine (py-core) | F80: P0 | G80: M1 | H80: S | I80: =IF(H80="S",0.5,IF(H80="M",1,IF(H80="L",2,0))) | J80: A | K80: backend | L80: Assigned | M80: Nostidus4 | N80: OPEN | O80: ENG-006 | P80: =IF(O80="",0,SUMPRODUCT(--ISNUMBER(SEARCH(", "&$A$2:$A$245&",",", "&O80&",")),--($L$2:$L$245<>"Done"))) | Q80: open
... A82: ENG-014 | B82: 260 | C82: [ENGINE] Build the borrow proposal | D82: financial-engine | E82: [EPIC] M07 · Financial Engine (py-core) | F82: P1 | G82: M1 | H82: S | I82: =IF(H82="S",0.5,IF(H82="M",1,IF(H82="L",2,0))) | J82: B | K82: backend | L82: Assigned | M82: Nostidus4 | N82: OPEN | O82: ENG-013 | P82: =IF(O82="",0,SUMPRODUCT(--ISNUMBER(SEARCH(", "&$A$2:$A$245&",",", "&O82&",")),--($L$2:$L$245<>"Done"))) | Q82: open
A83: ENG-L01 | B83: 101 | C83: [ENGINE] Plan refills from other operational wallets | D83: financial-engine | E83: [EPIC] M07 · Financial Engine (py-core) | F83: — | G83: Later | H83: M | I83: =IF(H83="S",0.5,IF(H83="M",1,IF(H83="L",2,0))) | J83: Later | K83: backend | L83: Accepted | N83: OPEN | O83: ENG-007, SC-L06 | P83: =IF(O83="",0,SUMPRODUCT(--ISNUMBER(SEARCH(", "&$A$2:$A$245&",",", "&O83&",")),--($L$2:$L$245<>"Done"))) | Q83: open
A84: ENG-L02 | B84: 102 | C84: [ENGINE] Add FX conversion and depeg checks for fiat invoices | D84: financial-engine | E84: [EPIC] M07 · Financial Engine (py-core) | F84: — | G84: Later | H84: M | I84: =IF(H84="S",0.5,IF(H84="M",1,IF(H84="L",2,0))) | J84: Later | K84: backend | L84: Accepted | N84: OPEN | O84: ENG-005 | P84: =IF(O84="",0,SUMPRODUCT(--ISNUMBER(SEARCH(", "&$A$2:$A$245&",",", "&O84&",")),--($L$2:$L$245<>"Done"))) | Q84: open
A85: ENG-L03 | B85: 103 | C85: [ENGINE] Extend the scheduler to multiple assets | D85: financial-engine | E85: [EPIC] M07 · Financial Engine (py-core) | F85: — | G85: Later | H85: M | I85: =IF(H85="S",0.5,IF(H85="M",1,IF(H85="L",2,0))) | J85: Later | K85: backend | L85: Accepted | N85: OPEN | O85: ENG-007 | P85: =IF(O85="",0,SUMPRODUCT(--ISNUMBER(SEARCH(", "&$A$2:$A$245&",",", "&O85&",")),--($L$2:$L$245<>"Done"))) | Q85: open
A86: EXE-001 | B86: 46 | C86: [EXECUTION] Create operations (outbox), transactions and gas ledger schema | D86: execution | E86: [EPIC] M10 · Orchestration & Execution | F86: P0 | G86: M1 | H86: S | I86: =IF(H86="S",0.5,IF(H86="M",1,IF(H86="L",2,0))) | J86: A | K86: backend | L86: Assigned | M86: Nostidus4 | N86: OPEN | O86: INV-001 | P86: =IF(O86="",0,SUMPRODUCT(--ISNUMBER(SEARCH(", "&$A$2:$A$245&",",", "&O86&",")),--($L$2:$L$245<>"Done"))) | Q86: open
A87: EXE-002 | B87: 131 | C87: [EXECUTION] Set up Celery with core and ai queues | D87: execution | E87: [EPIC] M10 · Orchestration & Execution | F87: P0 | G87: M1 | H87: M | I87: =IF(H87="S",0.5,IF(H87="M",1,IF(H87="L",2,0))) | J87: A | K87: backend | L87: Assigned | M87: Nostidus4 | N87: OPEN | O87: DEV-002 | P87: =IF(O87="",0,SUMPRODUCT(--ISNUMBER(SEARCH(", "&$A$2:$A$245&",",", "&O87&",")),--($L$2:$L$245<>"Done"))) | Q87: open
A88: EXE-003 | B88: 142 | C88: [EXECUTION] Implement the deadline trigger | D88: execution | E88: [EPIC] M10 · Orchestration & Execution | F88: P0 | G88: M1 | H88: M | I88: =IF(H88="S",0.5,IF(H88="M",1,IF(H88="L",2,0))) | J88: A | K88: backend | L88: Assigned | M88: Nostidus4 | N88: OPEN | O88: EXE-002, INV-010, MDT-007, TRS-007 | P88: =IF(O88="",0,SUMPRODUCT(--ISNUMBER(SEARCH(", "&$A$2:$A$245&",",", "&O88&",")),--($L$2:$L$245<>"Done"))) | Q88: open
A89: EXE-004 | B89: 146 | C89: [EXECUTION] Implement the planning pipeline task | D89: execution | E89: [EPIC] M10 · Orchestration & Execution | F89: P0 | G89: M1 | H89: L | I89: =IF(H89="S",0.5,IF(H89="M",1,IF(H89="L",2,0))) | J89: A | K89: backend | L89: Assigned | M89: Nostidus4 | N89: OPEN | O89: EXE-003, CHR-002, ENG-008, POL-006, AGT-009, EXE-012 | P89: =IF(O89="",0,SUMPRODUCT(--ISNUMBER(SEARCH(", "&$A$2:$A$245&",",", "&O89&",")),--($L$2:$L$245<>"Done"))) | Q89: open
A90: EXE-005 | B90: 60 | C90: [EXECUTION] Build the signer service | D90: execution | E90: [EPIC] M10 · Orchestration & Execution | F90: P0 | G90: M1 | H90: L | I90: =IF(H90="S",0.5,IF(H90="M",1,IF(H90="L",2,0))) | J90: A | K90: backend | L90: Assigned | M90: Nostidus4 | N90: OPEN | O90: POL-006, POL-007, SC-016 | P90: =IF(O90="",0,SUMPRODUCT(--ISNUMBER(SEARCH(", "&$A$2:$A$245&",",", "&O90&",")),--($L$2:$L$245<>"Done"))) | Q90: open
A91: EXE-006 | B91: 147 | C91: [EXECUTION] Load the executor key from an encrypted keystore | D91: execution | E91: [EPIC] M10 · Orchestration & Execution | F91: P0 | G91: M1 | H91: S | I91: =IF(H91="S",0.5,IF(H91="M",1,IF(H91="L",2,0))) | J91: A | K91: backend | L91: Assigned | M91: Nostidus4 | N91: OPEN | O91: EXE-005 | P91: =IF(O91="",0,SUMPRODUCT(--ISNUMBER(SEARCH(", "&$A$2:$A$245&",",", "&O91&",")),--($L$2:$L$245<>"Done"))) | Q91: open
A92: EXE-007 | B92: 61 | C92: [EXECUTION] Implement the executor with outbox semantics | D92: execution | E92: [EPIC] M10 · Orchestration & Execution | F92: P0 | G92: M1 | H92: M | I92: =IF(H92="S",0.5,IF(H92="M",1,IF(H92="L",2,0))) | J92: A | K92: backend | L92: Assigned | M92: Nostidus4 | N92: OPEN | O92: EXE-005, EXE-001 | P92: =IF(O92="",0,SUMPRODUCT(--ISNUMBER(SEARCH(", "&$A$2:$A$245&",",", "&O92&",")),--($L$2:$L$245<>"Done"))) | Q92: open
A93: EXE-008 | B93: 65 | C93: [EXECUTION] Sequence steps with re-read and re-validation | D93: execution | E93: [EPIC] M10 · Orchestration & Execution | F93: P0 | G93: M1 | H93: M | I93: =IF(H93="S",0.5,IF(H93="M",1,IF(H93="L",2,0))) | J93: A | K93: backend | L93: Assigned | M93: Nostidus4 | N93: OPEN | O93: EXE-007, CHR-003, POL-003, POL-007 | P93: =IF(O93="",0,SUMPRODUCT(--ISNUMBER(SEARCH(", "&$A$2:$A$245&",",", "&O93&",")),--($L$2:$L$245<>"Done"))) | Q93: open
A94: EXE-009 | B94: 148 | C94: [EXECUTION] Add the operator run-now endpoint | D94: execution | E94: [EPIC] M10 · Orchestration & Execution | F94: P1 | G94: M1 | H94: S | I94: =IF(H94="S",0.5,IF(H94="M",1,IF(H94="L",2,0))) | J94: After submission | K94: backend | L94: Assigned | M94: Nostidus4 | N94: OPEN | O94: EXE-003 | P94: =IF(O94="",0,SUMPRODUCT(--ISNUMBER(SEARCH(", "&$A$2:$A$245&",",", "&O94&",")),--($L$2:$L$245<>"Done"))) | Q94: open
A95: EXE-010 | B95: 149 | C95: [EXECUTION] Track gas fees and alert on low executor gas | D95: execution | E95: [EPIC] M10 · Orchestration & Execution | F95: P1 | G95: M1 | H95: S | I95: =IF(H95="S",0.5,IF(H95="M",1,IF(H95="L",2,0))) | J95: After submission | K95: backend | L95: Assigned | M95: Nostidus4 | N95: OPEN | O95: EXE-007 | P95: =IF(O95="",0,SUMPRODUCT(--ISNUMBER(SEARCH(", "&$A$2:$A$245&",",", "&O95&",")),--($L$2:$L$245<>"Done"))) | Q95: open
A96: EXE-011 | B96: 150 | C96: [EXECUTION] Execute the swap-for-gas step on the test router | D96: execution | E96: [EPIC] M10 · Orchestration & Execution | F96: P2 | G96: M1 | H96: S | I96: =IF(H96="S",0.5,IF(H96="M",1,IF(H96="L",2,0))) | J96: After submission | K96: backend | L96: Assigned | M96: Nostidus4 | N96: OPEN | O96: EXE-008, SC-018 | P96: =IF(O96="",0,SUMPRODUCT(--ISNUMBER(SEARCH(", "&$A$2:$A$245&",",", "&O96&",")),--($L$2:$L$245<>"Done"))) | Q96: open
A97: EXE-012 | B97: 249 | C97: [EXECUTION] Implement the fee policy, fee holds and fee acceptance | D97: execution | E97: [EPIC] M10 · Orchestration & Execution | F97: P0 | G97: M1 | H97: M | I97: =IF(H97="S",0.5,IF(H97="M",1,IF(H97="L",2,0))) | J97: A | K97: backend | L97: Assigned | M97: Nostidus4 | N97: OPEN | O97: MDT-001, CHR-001, ENG-001 | P97: =IF(O97="",0,SUMPRODUCT(--ISNUMBER(SEARCH(", "&$A$2:$A$245&",",", "&O97&",")),--($L$2:$L$245<>"Done"))) | Q97: open
... A99: EXE-014 | B99: 261 | C99: [EXECUTION] Run the liquidity cycle (supply / withdraw) | D99: execution | E99: [EPIC] M10 · Orchestration & Execution | F99: P0 | G99: M1 | H99: S | I99: =IF(H99="S",0.5,IF(H99="M",1,IF(H99="L",2,0))) | J99: A | K99: backend | L99: Assigned | M99: Nostidus4 | N99: OPEN | O99: EXE-008, ENG-013, SC-024 | P99: =IF(O99="",0,SUMPRODUCT(--ISNUMBER(SEARCH(", "&$A$2:$A$245&",",", "&O99&",")),--($L$2:$L$245<>"Done"))) | Q99: open
A100: EXE-L01 | B100: 151 | C100: [EXECUTION] Add a KMS-backed signer | D100: execution | E100: [EPIC] M10 · Orchestration & Execution | F100: — | G100: Later | H100: M | I100: =IF(H100="S",0.5,IF(H100="M",1,IF(H100="L",2,0))) | J100: Later | K100: backend | L100: Accepted | N100: OPEN | O100: EXE-005 | P100: =IF(O100="",0,SUMPRODUCT(--ISNUMBER(SEARCH(", "&$A$2:$A$245&",",", "&O100&",")),--($L$2:$L$245<>"Done"))) | Q100: open
A101: EXE-L02 | B101: 152 | C101: [EXECUTION] Integrate the production swap adapter | D101: execution | E101: [EPIC] M10 · Orchestration & Execution | F101: — | G101: Later | H101: M | I101: =IF(H101="S",0.5,IF(H101="M",1,IF(H101="L",2,0))) | J101: Later | K101: backend | L101: Accepted | N101: OPEN | O101: EXE-011, SC-L03 | P101: =IF(O101="",0,SUMPRODUCT(--ISNUMBER(SEARCH(", "&$A$2:$A$245&",",", "&O101&",")),--($L$2:$L$245<>"Done"))) | Q101: open
A102: EXE-L03 | B102: 153 | C102: [EXECUTION] Add cross-chain bridging | D102: execution | E102: [EPIC] M10 · Orchestration & Execution | F102: — | G102: Later | H102: L | I102: =IF(H102="S",0.5,IF(H102="M",1,IF(H102="L",2,0))) | J102: Later | K102: backend | L102: Accepted | N102: OPEN | O102: TRS-L01 | P102: =IF(O102="",0,SUMPRODUCT(--ISNUMBER(SEARCH(", "&$A$2:$A$245&",",", "&O102&",")),--($L$2:$L$245<>"Done"))) | Q102: open
A103: EXE-L04 | B103: 154 | C103: [EXECUTION] Partition workers by treasury for scale | D103: execution | E103: [EPIC] M10 · Orchestration & Execution | F103: — | G103: Later | H103: M | I103: =IF(H103="S",0.5,IF(H103="M",1,IF(H103="L",2,0))) | J103: Later | K103: backend | L103: Accepted | N103: OPEN | O103: EXE-002 | P103: =IF(O103="",0,SUMPRODUCT(--ISNUMBER(SEARCH(", "&$A$2:$A$245&",",", "&O103&",")),--($L$2:$L$245<>"Done"))) | Q103: open
A104: IDN-001 | B104: 32 | C104: [IDENTITY] Create identity database schema and migrations | D104: identity | E104: [EPIC] M01 · Identity & Access | F104: P0 | G104: M1 | H104: S | I104: =IF(H104="S",0.5,IF(H104="M",1,IF(H104="L",2,0))) | J104: A | K104: backend | L104: Assigned | M104: Nostidus4 | N104: OPEN | O104: DEV-002 | P104: =IF(O104="",0,SUMPRODUCT(--ISNUMBER(SEARCH(", "&$A$2:$A$245&",",", "&O104&",")),--($L$2:$L$245<>"Done"))) | Q104: open
A105: IDN-002 | B105: 37 | C105: [IDENTITY] Implement magic-link login, sessions and CSRF | D105: identity | E105: [EPIC] M01 · Identity & Access | F105: P0 | G105: M1 | H105: M | I105: =IF(H105="S",0.5,IF(H105="M",1,IF(H105="L",2,0))) | J105: A | K105: backend | L105: Assigned | M105: Nostidus4 | N105: OPEN | O105: IDN-001 | P105: =IF(O105="",0,SUMPRODUCT(--ISNUMBER(SEARCH(", "&$A$2:$A$245&",",", "&O105&",")),--($L$2:$L$245<>"Done"))) | Q105: open
A106: IDN-003 | B106: 105 | C106: [IDENTITY] Rate-limit authentication endpoints | D106: identity | E106: [EPIC] M01 · Identity & Access | F106: P0 | G106: M1 | H106: S | I106: =IF(H106="S",0.5,IF(H106="M",1,IF(H106="L",2,0))) | J106: B | K106: backend | L106: Assigned | M106: Nostidus4 | N106: OPEN | O106: IDN-002 | P106: =IF(O106="",0,SUMPRODUCT(--ISNUMBER(SEARCH(", "&$A$2:$A$245&",",", "&O106&",")),--($L$2:$L$245<>"Done"))) | Q106: open
A107: IDN-004 | B107: 106 | C107: [IDENTITY] Implement SIWE wallet linking | D107: identity | E107: [EPIC] M01 · Identity & Access | F107: P0 | G107: M1 | H107: M | I107: =IF(H107="S",0.5,IF(H107="M",1,IF(H107="L",2,0))) | J107: A | K107: backend | L107: Assigned | M107: Nostidus4 | N107: OPEN | O107: IDN-002 | P107: =IF(O107="",0,SUMPRODUCT(--ISNUMBER(SEARCH(", "&$A$2:$A$245&",",", "&O107&",")),--($L$2:$L$245<>"Done"))) | Q107: open
A108: IDN-005 | B108: 38 | C108: [IDENTITY] Implement organization creation and onboarding checklist | D108: identity | E108: [EPIC] M01 · Identity & Access | F108: P0 | G108: M1 | H108: S | I108: =IF(H108="S",0.5,IF(H108="M",1,IF(H108="L",2,0))) | J108: A | K108: backend | L108: Assigned | M108: Nostidus4 | N108: OPEN | O108: IDN-002 | P108: =IF(O108="",0,SUMPRODUCT(--ISNUMBER(SEARCH(", "&$A$2:$A$245&",",", "&O108&",")),--($L$2:$L$245<>"Done"))) | Q108: open
A109: IDN-006 | B109: 39 | C109: [IDENTITY] Implement RBAC dependencies and tenant isolation | D109: identity | E109: [EPIC] M01 · Identity & Access | F109: P0 | G109: M1 | H109: M | I109: =IF(H109="S",0.5,IF(H109="M",1,IF(H109="L",2,0))) | J109: A | K109: backend | L109: Assigned | M109: Nostidus4 | N109: OPEN | O109: IDN-005 | P109: =IF(O109="",0,SUMPRODUCT(--ISNUMBER(SEARCH(", "&$A$2:$A$245&",",", "&O109&",")),--($L$2:$L$245<>"Done"))) | Q109: open
A110: IDN-007 | B110: 107 | C110: [IDENTITY] Implement invites and membership management | D110: identity | E110: [EPIC] M01 · Identity & Access | F110: P1 | G110: M1 | H110: M | I110: =IF(H110="S",0.5,IF(H110="M",1,IF(H110="L",2,0))) | J110: After submission | K110: backend | L110: Assigned | M110: Nostidus4 | N110: OPEN | O110: IDN-006 | P110: =IF(O110="",0,SUMPRODUCT(--ISNUMBER(SEARCH(", "&$A$2:$A$245&",",", "&O110&",")),--($L$2:$L$245<>"Done"))) | Q110: open
...

Sheet Module Progress
A1: Module | B1: Tickets | C1: Done | D1: In Progress | E1: Review | F1: Not started | G1: % done (count) | H1: Est. days | I1: Est. days done | J1: % done (effort) | K1: Cut A tickets | L1: Cut A done | M1: % Cut A done
A2: admin | B2: =COUNTIFS(Issues!$D$2:$D$245,A2) | C2: =COUNTIFS(Issues!$D$2:$D$245,A2,Issues!$L$2:$L$245,"Done") | D2: =COUNTIFS(Issues!$D$2:$D$245,A2,Issues!$L$2:$L$245,"In Progress") | E2: =COUNTIFS(Issues!$D$2:$D$245,A2,Issues!$L$2:$L$245,"Review") | F2: =B2-C2-D2-E2 | G2: =IF(B2=0,0,C2/B2) | H2: =SUMIFS(Issues!$I$2:$I$245,Issues!$D$2:$D$245,A2) | I2: =SUMIFS(Issues!$I$2:$I$245,Issues!$D$2:$D$245,A2,Issues!$L$2:$L$245,"Done") | J2: =IF(H2=0,0,I2/H2) | K2: =COUNTIFS(Issues!$D$2:$D$245,A2,Issues!$J$2:$J$245,"A") | L2: =COUNTIFS(Issues!$D$2:$D$245,A2,Issues!$J$2:$J$245,"A",Issues!$L$2:$L$245,"Done") | M2: =IF(K2=0,0,L2/K2)
A3: agent | B3: =COUNTIFS(Issues!$D$2:$D$245,A3) | C3: =COUNTIFS(Issues!$D$2:$D$245,A3,Issues!$L$2:$L$245,"Done") | D3: =COUNTIFS(Issues!$D$2:$D$245,A3,Issues!$L$2:$L$245,"In Progress") | E3: =COUNTIFS(Issues!$D$2:$D$245,A3,Issues!$L$2:$L$245,"Review") | F3: =B3-C3-D3-E3 | G3: =IF(B3=0,0,C3/B3) | H3: =SUMIFS(Issues!$I$2:$I$245,Issues!$D$2:$D$245,A3) | I3: =SUMIFS(Issues!$I$2:$I$245,Issues!$D$2:$D$245,A3,Issues!$L$2:$L$245,"Done") | J3: =IF(H3=0,0,I3/H3) | K3: =COUNTIFS(Issues!$D$2:$D$245,A3,Issues!$J$2:$J$245,"A") | L3: =COUNTIFS(Issues!$D$2:$D$245,A3,Issues!$J$2:$J$245,"A",Issues!$L$2:$L$245,"Done") | M3: =IF(K3=0,0,L3/K3)
A4: audit | B4: =COUNTIFS(Issues!$D$2:$D$245,A4) | C4: =COUNTIFS(Issues!$D$2:$D$245,A4,Issues!$L$2:$L$245,"Done") | D4: =COUNTIFS(Issues!$D$2:$D$245,A4,Issues!$L$2:$L$245,"In Progress") | E4: =COUNTIFS(Issues!$D$2:$D$245,A4,Issues!$L$2:$L$245,"Review") | F4: =B4-C4-D4-E4 | G4: =IF(B4=0,0,C4/B4) | H4: =SUMIFS(Issues!$I$2:$I$245,Issues!$D$2:$D$245,A4) | I4: =SUMIFS(Issues!$I$2:$I$245,Issues!$D$2:$D$245,A4,Issues!$L$2:$L$245,"Done") | J4: =IF(H4=0,0,I4/H4) | K4: =COUNTIFS(Issues!$D$2:$D$245,A4,Issues!$J$2:$J$245,"A") | L4: =COUNTIFS(Issues!$D$2:$D$245,A4,Issues!$J$2:$J$245,"A",Issues!$L$2:$L$245,"Done") | M4: =IF(K4=0,0,L4/K4)
A5: chain-reader | B5: =COUNTIFS(Issues!$D$2:$D$245,A5) | C5: =COUNTIFS(Issues!$D$2:$D$245,A5,Issues!$L$2:$L$245,"Done") | D5: =COUNTIFS(Issues!$D$2:$D$245,A5,Issues!$L$2:$L$245,"In Progress") | E5: =COUNTIFS(Issues!$D$2:$D$245,A5,Issues!$L$2:$L$245,"Review") | F5: =B5-C5-D5-E5 | G5: =IF(B5=0,0,C5/B5) | H5: =SUMIFS(Issues!$I$2:$I$245,Issues!$D$2:$D$245,A5) | I5: =SUMIFS(Issues!$I$2:$I$245,Issues!$D$2:$D$245,A5,Issues!$L$2:$L$245,"Done") | J5: =IF(H5=0,0,I5/H5) | K5: =COUNTIFS(Issues!$D$2:$D$245,A5,Issues!$J$2:$J$245,"A") | L5: =COUNTIFS(Issues!$D$2:$D$245,A5,Issues!$J$2:$J$245,"A",Issues!$L$2:$L$245,"Done") | M5: =IF(K5=0,0,L5/K5)
A6: compliance | B6: =COUNTIFS(Issues!$D$2:$D$245,A6) | C6: =COUNTIFS(Issues!$D$2:$D$245,A6,Issues!$L$2:$L$245,"Done") | D6: =COUNTIFS(Issues!$D$2:$D$245,A6,Issues!$L$2:$L$245,"In Progress") | E6: =COUNTIFS(Issues!$D$2:$D$245,A6,Issues!$L$2:$L$245,"Review") | F6: =B6-C6-D6-E6 | G6: =IF(B6=0,0,C6/B6) | H6: =SUMIFS(Issues!$I$2:$I$245,Issues!$D$2:$D$245,A6) | I6: =SUMIFS(Issues!$I$2:$I$245,Issues!$D$2:$D$245,A6,Issues!$L$2:$L$245,"Done") | J6: =IF(H6=0,0,I6/H6) | K6: =COUNTIFS(Issues!$D$2:$D$245,A6,Issues!$J$2:$J$245,"A") | L6: =COUNTIFS(Issues!$D$2:$D$245,A6,Issues!$J$2:$J$245,"A",Issues!$L$2:$L$245,"Done") | M6: =IF(K6=0,0,L6/K6)
A7: contracts | B7: =COUNTIFS(Issues!$D$2:$D$245,A7) | C7: =COUNTIFS(Issues!$D$2:$D$245,A7,Issues!$L$2:$L$245,"Done") | D7: =COUNTIFS(Issues!$D$2:$D$245,A7,Issues!$L$2:$L$245,"In Progress") | E7: =COUNTIFS(Issues!$D$2:$D$245,A7,Issues!$L$2:$L$245,"Review") | F7: =B7-C7-D7-E7 | G7: =IF(B7=0,0,C7/B7) | H7: =SUMIFS(Issues!$I$2:$I$245,Issues!$D$2:$D$245,A7) | I7: =SUMIFS(Issues!$I$2:$I$245,Issues!$D$2:$D$245,A7,Issues!$L$2:$L$245,"Done") | J7: =IF(H7=0,0,I7/H7) | K7: =COUNTIFS(Issues!$D$2:$D$245,A7,Issues!$J$2:$J$245,"A") | L7: =COUNTIFS(Issues!$D$2:$D$245,A7,Issues!$J$2:$J$245,"A",Issues!$L$2:$L$245,"Done") | M7: =IF(K7=0,0,L7/K7)
A8: devex | B8: =COUNTIFS(Issues!$D$2:$D$245,A8) | C8: =COUNTIFS(Issues!$D$2:$D$245,A8,Issues!$L$2:$L$245,"Done") | D8: =COUNTIFS(Issues!$D$2:$D$245,A8,Issues!$L$2:$L$245,"In Progress") | E8: =COUNTIFS(Issues!$D$2:$D$245,A8,Issues!$L$2:$L$245,"Review") | F8: =B8-C8-D8-E8 | G8: =IF(B8=0,0,C8/B8) | H8: =SUMIFS(Issues!$I$2:$I$245,Issues!$D$2:$D$245,A8) | I8: =SUMIFS(Issues!$I$2:$I$245,Issues!$D$2:$D$245,A8,Issues!$L$2:$L$245,"Done") | J8: =IF(H8=0,0,I8/H8) | K8: =COUNTIFS(Issues!$D$2:$D$245,A8,Issues!$J$2:$J$245,"A") | L8: =COUNTIFS(Issues!$D$2:$D$245,A8,Issues!$J$2:$J$245,"A",Issues!$L$2:$L$245,"Done") | M8: =IF(K8=0,0,L8/K8)
A9: domain-evidence | B9: =COUNTIFS(Issues!$D$2:$D$245,A9) | C9: =COUNTIFS(Issues!$D$2:$D$245,A9,Issues!$L$2:$L$245,"Done") | D9: =COUNTIFS(Issues!$D$2:$D$245,A9,Issues!$L$2:$L$245,"In Progress") | E9: =COUNTIFS(Issues!$D$2:$D$245,A9,Issues!$L$2:$L$245,"Review") | F9: =B9-C9-D9-E9 | G9: =IF(B9=0,0,C9/B9) | H9: =SUMIFS(Issues!$I$2:$I$245,Issues!$D$2:$D$245,A9) | I9: =SUMIFS(Issues!$I$2:$I$245,Issues!$D$2:$D$245,A9,Issues!$L$2:$L$245,"Done") | J9: =IF(H9=0,0,I9/H9) | K9: =COUNTIFS(Issues!$D$2:$D$245,A9,Issues!$J$2:$J$245,"A") | L9: =COUNTIFS(Issues!$D$2:$D$245,A9,Issues!$J$2:$J$245,"A",Issues!$L$2:$L$245,"Done") | M9: =IF(K9=0,0,L9/K9)
A10: execution | B10: =COUNTIFS(Issues!$D$2:$D$245,A10) | C10: =COUNTIFS(Issues!$D$2:$D$245,A10,Issues!$L$2:$L$245,"Done") | D10: =COUNTIFS(Issues!$D$2:$D$245,A10,Issues!$L$2:$L$245,"In Progress") | E10: =COUNTIFS(Issues!$D$2:$D$245,A10,Issues!$L$2:$L$245,"Review") | F10: =B10-C10-D10-E10 | G10: =IF(B10=0,0,C10/B10) | H10: =SUMIFS(Issues!$I$2:$I$245,Issues!$D$2:$D$245,A10) | I10: =SUMIFS(Issues!$I$2:$I$245,Issues!$D$2:$D$245,A10,Issues!$L$2:$L$245,"Done") | J10: =IF(H10=0,0,I10/H10) | K10: =COUNTIFS(Issues!$D$2:$D$245,A10,Issues!$J$2:$J$245,"A") | L10: =COUNTIFS(Issues!$D$2:$D$245,A10,Issues!$J$2:$J$245,"A",Issues!$L$2:$L$245,"Done") | M10: =IF(K10=0,0,L10/K10)
A11: financial-engine | B11: =COUNTIFS(Issues!$D$2:$D$245,A11) | C11: =COUNTIFS(Issues!$D$2:$D$245,A11,Issues!$L$2:$L$245,"Done") | D11: =COUNTIFS(Issues!$D$2:$D$245,A11,Issues!$L$2:$L$245,"In Progress") | E11: =COUNTIFS(Issues!$D$2:$D$245,A11,Issues!$L$2:$L$245,"Review") | F11: =B11-C11-D11-E11 | G11: =IF(B11=0,0,C11/B11) | H11: =SUMIFS(Issues!$I$2:$I$245,Issues!$D$2:$D$245,A11) | I11: =SUMIFS(Issues!$I$2:$I$245,Issues!$D$2:$D$245,A11,Issues!$L$2:$L$245,"Done") | J11: =IF(H11=0,0,I11/H11) | K11: =COUNTIFS(Issues!$D$2:$D$245,A11,Issues!$J$2:$J$245,"A") | L11: =COUNTIFS(Issues!$D$2:$D$245,A11,Issues!$J$2:$J$245,"A",Issues!$L$2:$L$245,"Done") | M11: =IF(K11=0,0,L11/K11)
A12: identity | B12: =COUNTIFS(Issues!$D$2:$D$245,A12) | C12: =COUNTIFS(Issues!$D$2:$D$245,A12,Issues!$L$2:$L$245,"Done") | D12: =COUNTIFS(Issues!$D$2:$D$245,A12,Issues!$L$2:$L$245,"In Progress") | E12: =COUNTIFS(Issues!$D$2:$D$245,A12,Issues!$L$2:$L$245,"Review") | F12: =B12-C12-D12-E12 | G12: =IF(B12=0,0,C12/B12) | H12: =SUMIFS(Issues!$I$2:$I$245,Issues!$D$2:$D$245,A12) | I12: =SUMIFS(Issues!$I$2:$I$245,Issues!$D$2:$D$245,A12,Issues!$L$2:$L$245,"Done") | J12: =IF(H12=0,0,I12/H12) | K12: =COUNTIFS(Issues!$D$2:$D$245,A12,Issues!$J$2:$J$245,"A") | L12: =COUNTIFS(Issues!$D$2:$D$245,A12,Issues!$J$2:$J$245,"A",Issues!$L$2:$L$245,"Done") | M12: =IF(K12=0,0,L12/K12)
A13: invoices | B13: =COUNTIFS(Issues!$D$2:$D$245,A13) | C13: =COUNTIFS(Issues!$D$2:$D$245,A13,Issues!$L$2:$L$245,"Done") | D13: =COUNTIFS(Issues!$D$2:$D$245,A13,Issues!$L$2:$L$245,"In Progress") | E13: =COUNTIFS(Issues!$D$2:$D$245,A13,Issues!$L$2:$L$245,"Review") | F13: =B13-C13-D13-E13 | G13: =IF(B13=0,0,C13/B13) | H13: =SUMIFS(Issues!$I$2:$I$245,Issues!$D$2:$D$245,A13) | I13: =SUMIFS(Issues!$I$2:$I$245,Issues!$D$2:$D$245,A13,Issues!$L$2:$L$245,"Done") | J13: =IF(H13=0,0,I13/H13) | K13: =COUNTIFS(Issues!$D$2:$D$245,A13,Issues!$J$2:$J$245,"A") | L13: =COUNTIFS(Issues!$D$2:$D$245,A13,Issues!$J$2:$J$245,"A",Issues!$L$2:$L$245,"Done") | M13: =IF(K13=0,0,L13/K13)
... A21: web | B21: =COUNTIFS(Issues!$D$2:$D$245,A21) | C21: =COUNTIFS(Issues!$D$2:$D$245,A21,Issues!$L$2:$L$245,"Done") | D21: =COUNTIFS(Issues!$D$2:$D$245,A21,Issues!$L$2:$L$245,"In Progress") | E21: =COUNTIFS(Issues!$D$2:$D$245,A21,Issues!$L$2:$L$245,"Review") | F21: =B21-C21-D21-E21 | G21: =IF(B21=0,0,C21/B21) | H21: =SUMIFS(Issues!$I$2:$I$245,Issues!$D$2:$D$245,A21) | I21: =SUMIFS(Issues!$I$2:$I$245,Issues!$D$2:$D$245,A21,Issues!$L$2:$L$245,"Done") | J21: =IF(H21=0,0,I21/H21) | K21: =COUNTIFS(Issues!$D$2:$D$245,A21,Issues!$J$2:$J$245,"A") | L21: =COUNTIFS(Issues!$D$2:$D$245,A21,Issues!$J$2:$J$245,"A",Issues!$L$2:$L$245,"Done") | M21: =IF(K21=0,0,L21/K21)
A22: TOTAL | B22: =SUM(B2:B21) | C22: =SUM(C2:C21) | D22: =SUM(D2:D21) | E22: =SUM(E2:E21) | F22: =SUM(F2:F21) | G22: =IF(B22=0,0,C22/B22) | H22: =SUM(H2:H21) | I22: =SUM(I2:I21) | J22: =IF(H22=0,0,I22/H22) | K22: =SUM(K2:K21) | L22: =SUM(L2:L21) | M22: =IF(K22=0,0,L22/K22)

Sheet Status Summary
A1: Status | B1: All tickets | C1: Cut A | D1: Cut B | E1: M1 | F1: Later
A2: Draft | B2: =COUNTIFS(Issues!$L$2:$L$245,A2) | C2: =COUNTIFS(Issues!$L$2:$L$245,A2,Issues!$J$2:$J$245,"A") | D2: =COUNTIFS(Issues!$L$2:$L$245,A2,Issues!$J$2:$J$245,"B") | E2: =COUNTIFS(Issues!$L$2:$L$245,A2,Issues!$G$2:$G$245,"M1") | F2: =COUNTIFS(Issues!$L$2:$L$245,A2,Issues!$G$2:$G$245,"Later")
A3: Needs Discussion | B3: =COUNTIFS(Issues!$L$2:$L$245,A3) | C3: =COUNTIFS(Issues!$L$2:$L$245,A3,Issues!$J$2:$J$245,"A") | D3: =COUNTIFS(Issues!$L$2:$L$245,A3,Issues!$J$2:$J$245,"B") | E3: =COUNTIFS(Issues!$L$2:$L$245,A3,Issues!$G$2:$G$245,"M1") | F3: =COUNTIFS(Issues!$L$2:$L$245,A3,Issues!$G$2:$G$245,"Later")
A4: Ready for Review | B4: =COUNTIFS(Issues!$L$2:$L$245,A4) | C4: =COUNTIFS(Issues!$L$2:$L$245,A4,Issues!$J$2:$J$245,"A") | D4: =COUNTIFS(Issues!$L$2:$L$245,A4,Issues!$J$2:$J$245,"B") | E4: =COUNTIFS(Issues!$L$2:$L$245,A4,Issues!$G$2:$G$245,"M1") | F4: =COUNTIFS(Issues!$L$2:$L$245,A4,Issues!$G$2:$G$245,"Later")
A5: Accepted | B5: =COUNTIFS(Issues!$L$2:$L$245,A5) | C5: =COUNTIFS(Issues!$L$2:$L$245,A5,Issues!$J$2:$J$245,"A") | D5: =COUNTIFS(Issues!$L$2:$L$245,A5,Issues!$J$2:$J$245,"B") | E5: =COUNTIFS(Issues!$L$2:$L$245,A5,Issues!$G$2:$G$245,"M1") | F5: =COUNTIFS(Issues!$L$2:$L$245,A5,Issues!$G$2:$G$245,"Later")
A6: Ready for Assignment | B6: =COUNTIFS(Issues!$L$2:$L$245,A6) | C6: =COUNTIFS(Issues!$L$2:$L$245,A6,Issues!$J$2:$J$245,"A") | D6: =COUNTIFS(Issues!$L$2:$L$245,A6,Issues!$J$2:$J$245,"B") | E6: =COUNTIFS(Issues!$L$2:$L$245,A6,Issues!$G$2:$G$245,"M1") | F6: =COUNTIFS(Issues!$L$2:$L$245,A6,Issues!$G$2:$G$245,"Later")
A7: Assigned | B7: =COUNTIFS(Issues!$L$2:$L$245,A7) | C7: =COUNTIFS(Issues!$L$2:$L$245,A7,Issues!$J$2:$J$245,"A") | D7: =COUNTIFS(Issues!$L$2:$L$245,A7,Issues!$J$2:$J$245,"B") | E7: =COUNTIFS(Issues!$L$2:$L$245,A7,Issues!$G$2:$G$245,"M1") | F7: =COUNTIFS(Issues!$L$2:$L$245,A7,Issues!$G$2:$G$245,"Later")
A8: In Progress | B8: =COUNTIFS(Issues!$L$2:$L$245,A8) | C8: =COUNTIFS(Issues!$L$2:$L$245,A8,Issues!$J$2:$J$245,"A") | D8: =COUNTIFS(Issues!$L$2:$L$245,A8,Issues!$J$2:$J$245,"B") | E8: =COUNTIFS(Issues!$L$2:$L$245,A8,Issues!$G$2:$G$245,"M1") | F8: =COUNTIFS(Issues!$L$2:$L$245,A8,Issues!$G$2:$G$245,"Later")
A9: Review | B9: =COUNTIFS(Issues!$L$2:$L$245,A9) | C9: =COUNTIFS(Issues!$L$2:$L$245,A9,Issues!$J$2:$J$245,"A") | D9: =COUNTIFS(Issues!$L$2:$L$245,A9,Issues!$J$2:$J$245,"B") | E9: =COUNTIFS(Issues!$L$2:$L$245,A9,Issues!$G$2:$G$245,"M1") | F9: =COUNTIFS(Issues!$L$2:$L$245,A9,Issues!$G$2:$G$245,"Later")
A10: Done | B10: =COUNTIFS(Issues!$L$2:$L$245,A10) | C10: =COUNTIFS(Issues!$L$2:$L$245,A10,Issues!$J$2:$J$245,"A") | D10: =COUNTIFS(Issues!$L$2:$L$245,A10,Issues!$J$2:$J$245,"B") | E10: =COUNTIFS(Issues!$L$2:$L$245,A10,Issues!$G$2:$G$245,"M1") | F10: =COUNTIFS(Issues!$L$2:$L$245,A10,Issues!$G$2:$G$245,"Later")
A11: TOTAL | B11: =SUM(B2:B10) | C11: =SUM(C2:C10) | D11: =SUM(D2:D10) | E11: =SUM(E2:E10) | F11: =SUM(F2:F10)
A13: Generated | B13: 2026-10-11 19:03 | C13: from GitHub Project | D13: https://github.com/users/Nostidus4/projects/1

Sheet Dependencies
A1: Ticket | B1: Blocked by | C1: Ticket status | D1: Blocker status | E1: Blocking now?
A2: ADM-L01 | B2: IDN-006 | C2: =IFERROR(INDEX(Issues!$L$2:$L$245,MATCH(A2,Issues!$A$2:$A$245,0)),"") | D2: =IFERROR(INDEX(Issues!$L$2:$L$245,MATCH(B2,Issues!$A$2:$A$245,0)),"") | E2: =IF(AND(C2<>"Done",D2<>"Done"),"Yes","No")
A3: ADM-L02 | B3: OBS-004 | C3: =IFERROR(INDEX(Issues!$L$2:$L$245,MATCH(A3,Issues!$A$2:$A$245,0)),"") | D3: =IFERROR(INDEX(Issues!$L$2:$L$245,MATCH(B3,Issues!$A$2:$A$245,0)),"") | E3: =IF(AND(C3<>"Done",D3<>"Done"),"Yes","No")
A4: ADM-L03 | B4: ADM-L02 | C4: =IFERROR(INDEX(Issues!$L$2:$L$245,MATCH(A4,Issues!$A$2:$A$245,0)),"") | D4: =IFERROR(INDEX(Issues!$L$2:$L$245,MATCH(B4,Issues!$A$2:$A$245,0)),"") | E4: =IF(AND(C4<>"Done",D4<>"Done"),"Yes","No")
A5: AGT-001 | B5: EXE-002 | C5: =IFERROR(INDEX(Issues!$L$2:$L$245,MATCH(A5,Issues!$A$2:$A$245,0)),"") | D5: =IFERROR(INDEX(Issues!$L$2:$L$245,MATCH(B5,Issues!$A$2:$A$245,0)),"") | E5: =IF(AND(C5<>"Done",D5<>"Done"),"Yes","No")
A6: AGT-002 | B6: AGT-001 | C6: =IFERROR(INDEX(Issues!$L$2:$L$245,MATCH(A6,Issues!$A$2:$A$245,0)),"") | D6: =IFERROR(INDEX(Issues!$L$2:$L$245,MATCH(B6,Issues!$A$2:$A$245,0)),"") | E6: =IF(AND(C6<>"Done",D6<>"Done"),"Yes","No")
A7: AGT-003 | B7: AGT-001 | C7: =IFERROR(INDEX(Issues!$L$2:$L$245,MATCH(A7,Issues!$A$2:$A$245,0)),"") | D7: =IFERROR(INDEX(Issues!$L$2:$L$245,MATCH(B7,Issues!$A$2:$A$245,0)),"") | E7: =IF(AND(C7<>"Done",D7<>"Done"),"Yes","No")
A8: AGT-004 | B8: AGT-003 | C8: =IFERROR(INDEX(Issues!$L$2:$L$245,MATCH(A8,Issues!$A$2:$A$245,0)),"") | D8: =IFERROR(INDEX(Issues!$L$2:$L$245,MATCH(B8,Issues!$A$2:$A$245,0)),"") | E8: =IF(AND(C8<>"Done",D8<>"Done"),"Yes","No")
A9: AGT-004 | B9: AGT-002 | C9: =IFERROR(INDEX(Issues!$L$2:$L$245,MATCH(A9,Issues!$A$2:$A$245,0)),"") | D9: =IFERROR(INDEX(Issues!$L$2:$L$245,MATCH(B9,Issues!$A$2:$A$245,0)),"") | E9: =IF(AND(C9<>"Done",D9<>"Done"),"Yes","No")
A10: AGT-004 | B10: INV-004 | C10: =IFERROR(INDEX(Issues!$L$2:$L$245,MATCH(A10,Issues!$A$2:$A$245,0)),"") | D10: =IFERROR(INDEX(Issues!$L$2:$L$245,MATCH(B10,Issues!$A$2:$A$245,0)),"") | E10: =IF(AND(C10<>"Done",D10<>"Done"),"Yes","No")
A11: AGT-005 | B11: AGT-004 | C11: =IFERROR(INDEX(Issues!$L$2:$L$245,MATCH(A11,Issues!$A$2:$A$245,0)),"") | D11: =IFERROR(INDEX(Issues!$L$2:$L$245,MATCH(B11,Issues!$A$2:$A$245,0)),"") | E11: =IF(AND(C11<>"Done",D11<>"Done"),"Yes","No")
A12: AGT-005 | B12: ENG-005 | C12: =IFERROR(INDEX(Issues!$L$2:$L$245,MATCH(A12,Issues!$A$2:$A$245,0)),"") | D12: =IFERROR(INDEX(Issues!$L$2:$L$245,MATCH(B12,Issues!$A$2:$A$245,0)),"") | E12: =IF(AND(C12<>"Done",D12<>"Done"),"Yes","No")
A13: AGT-006 | B13: AGT-004 | C13: =IFERROR(INDEX(Issues!$L$2:$L$245,MATCH(A13,Issues!$A$2:$A$245,0)),"") | D13: =IFERROR(INDEX(Issues!$L$2:$L$245,MATCH(B13,Issues!$A$2:$A$245,0)),"") | E13: =IF(AND(C13<>"Done",D13<>"Done"),"Yes","No")
... A372: WEB-027 | B372: ENG-014 | C372: =IFERROR(INDEX(Issues!$L$2:$L$245,MATCH(A372,Issues!$A$2:$A$245,0)),"") | D372: =IFERROR(INDEX(Issues!$L$2:$L$245,MATCH(B372,Issues!$A$2:$A$245,0)),"") | E372: =IF(AND(C372<>"Done",D372<>"Done"),"Yes","No")

Sheet How to use
A1: This workbook is a REPORT. GitHub (Project 'TreasuryPilot · Delivery') is the source of truth.
A2: To refresh: uv run --with openpyxl python planning/tracker/build_tracker.py
A3: Do not edit statuses here; change them in the GitHub Project, then rebuild.
A4: Status (column L, Issues) has a dropdown only for quick what-if analysis; changes are not synced back.
A5: Est. days: S = 0.5, M = 1, L = 2 (planning estimates; not re-estimated by developers).
A6: Open blockers = number of tickets listed in 'Blocked by' whose status is not Done.
A7: Cut: A = required for the submission demo, B = stretch, After submission / Later = planned after 20/10.
